clustaar/__init__.py
clustaar/spellz/api_client.py
clustaar.spellz.api_client-0.29.0.dist-info/LICENSE.txt
clustaar.spellz.api_client-0.29.0.dist-info/METADATA
clustaar.spellz.api_client-0.29.0.dist-info/WHEEL
clustaar.spellz.api_client-0.29.0.dist-info/top_level.txt
clustaar.spellz.api_client-0.29.0.dist-info/RECORD
