Metadata-Version: 2.1
Name: clustaar.spellz.api_client
Version: 0.29.0
Summary: Simple package for communicate with the spellz api
Home-page: https://github.com/pyscaffold/pyscaffold/
Author: schafers
Author-email: axel.schafers@gmail.com
License: MIT
Project-URL: Documentation, https://pyscaffold.org/
Platform: any
Classifier: Development Status :: 4 - Beta
Classifier: Programming Language :: Python
License-File: LICENSE.txt
Requires-Dist: ujson
Requires-Dist: requests
Requires-Dist: importlib-metadata ; python_version < "3.8"
Provides-Extra: testing
Requires-Dist: setuptools ; extra == 'testing'
Requires-Dist: pytest ; extra == 'testing'
Requires-Dist: pytest-cov ; extra == 'testing'
